{"name": "Консервы", "code": 637, "products": [{"id": 28318, "name": "Паштет Гастроном №1, нежный, 90 г", "mech": null, "img_link": "https://media.5ka.ru/media/products/3609913.jpg", "plu": 3609913, "promo": {"id": 1171092812, "date_begin": "2021-04-08", "date_end": "2021-05-05", "type": "", "description": "", "kind": "Z011", "expired_at": 14}, "current_prices": {"price_reg__min": 22.0, "price_promo__min": 16.99}, "store_name": null}, {"id": 28319, "name": "Паштет Гастроном №1, деликатесный, 90 г", "mech": null, "img_link": "https://media.5ka.ru/media/products/3609914.jpg", "plu": 3609914, "promo": {"id": 1171092812, "date_begin": "2021-04-08", "date_end": "2021-05-05", "type": "", "description": "", "kind": "Z011", "expired_at": 14}, "current_prices": {"price_reg__min": 22.0, "price_promo__min": 16.99}, "store_name": null}, {"id": 28317, "name": "Каша Губернаторская по-домашнему Главпродукт гречневая с говядиной 340 г", "mech": null, "img_link": "https://media.5ka.ru/media/products/3609254.jpg", "plu": 3609254, "promo": {"id": 1171092812, "date_begin": "2021-04-08", "date_end": "2021-05-05", "type": "", "description": "", "kind": "Z011", "expired_at": 14}, "current_prices": {"price_reg__min": 34.99, "price_promo__min": 32.99}, "store_name": null}, {"id": 31117, "name": "Консервы мясорастительные паштетные стерилизованные Hame Паштет деликатесный с гусиной печенью 105 г", "mech": null, "img_link": "https://media.5ka.ru/media/products/3959234.jpg", "plu": 3959234, "promo": {"id": 1170285965, "date_begin": "2021-04-01", "date_end": "2021-05-05", "type": "", "description": "", "kind": "Z011", "expired_at": 14}, "current_prices": {"price_reg__min": 42.99, "price_promo__min": 34.99}, "store_name": null}, {"id": 31930, "name": "Консервы мясорастительные паштетные стерилизованные Hame Паштет деликатесный с индейкой 105 г", "mech": null, "img_link": "https://media.5ka.ru/media/products/3959235.jpg", "plu": 3959235, "promo": {"id": 1170306661, "date_begin": "2021-04-01", "date_end": "2021-05-05", "type": "", "description": "", "kind": "Z011", "expired_at": 14}, "current_prices": {"price_reg__min": 42.99, "price_promo__min": 34.99}, "store_name": null}, {"id": 31931, "name": "Консервы мясорастительные паштетные стерилизованные Hame Паштет деликатесный с мясом птицы 105 г", "mech": null, "img_link": "https://media.5ka.ru/media/products/3959236.jpg", "plu": 3959236, "promo": {"id": 1170306661, "date_begin": "2021-04-01", "date_end": "2021-05-05", "type": "", "description": "", "kind": "Z011", "expired_at": 14}, "current_prices": {"price_reg__min": 42.99, "price_promo__min": 34.99}, "store_name": null}, {"id": 3860, "name": "Икра из бакалажанов, Global Village, 520 г", "mech": null, "img_link": "https://media.5ka.ru/media/products/3903537.jpg", "plu": 3903537, "promo": {"id": 1173707621, "date_begin": "2021-04-20", "date_end": "2021-04-26", "type": "", "description": "", "kind": "Z001", "expired_at": 5}, "current_prices": {"price_reg__min": 66.75, "price_promo__min": 49.9}, "store_name": null}, {"id": 3861, "name": "Консервы икра из кабачков 520г", "mech": null, "img_link": "https://media.5ka.ru/media/products/3903538.jpg", "plu": 3903538, "promo": {"id": 1173707621, "date_begin": "2021-04-20", "date_end": "2021-04-26", "type": "", "description": "", "kind": "Z001", "expired_at": 5}, "current_prices": {"price_reg__min": 59.99, "price_promo__min": 49.9}, "store_name": null}, {"id": 31808, "name": "GL.VILLAGE Рагу овощное 510г", "mech": null, "img_link": "https://media.5ka.ru/media/products/3602896.jpg", "plu": 3602896, "promo": {"id": 1170306661, "date_begin": "2021-04-01", "date_end": "2021-05-05", "type": "", "description": "", "kind": "Z011", "expired_at": 14}, "current_prices": {"price_reg__min": 64.95, "price_promo__min": 49.99}, "store_name": null}, {"id": 31816, "name": "Имбирь \"СКАТЕРТЬ-САМОБРАНКА\" маринованный с/б 200гр", "mech": null, "img_link": "https://media.5ka.ru/media/products/3605848.jpg", "plu": 3605848, "promo": {"id": 1170306661, "date_begin": "2021-04-01", "date_end": "2021-05-05", "type": "", "description": "", "kind": "Z011", "expired_at": 14}, "current_prices": {"price_reg__min": 67.25, "price_promo__min": 54.99}, "store_name": null}, {"id": 3794, "name": "Говядина тушеная Калининградская СТО 338 гр", "mech": null, "img_link": "https://media.5ka.ru/media/products/3609488.jpg", "plu": 3609488, "promo": {"id": 1173707621, "date_begin": "2021-04-20", "date_end": "2021-04-26", "type": "", "description": "", "kind": "Z001", "expired_at": 5}, "current_prices": {"price_reg__min": 86.0, "price_promo__min": 65.99}, "store_name": null}, {"id": 3765, "name": "Шпроты в масле, с ключом, Вкусные консервы, 160 г", "mech": null, "img_link": "https://media.5ka.ru/media/products/3475329.jpg", "plu": 3475329, "promo": {"id": 1173707621, "date_begin": "2021-04-20", "date_end": "2021-04-26", "type": "", "description": "", "kind": "Z001", "expired_at": 5}, "current_prices": {"price_reg__min": 89.99, "price_promo__min": 69.99}, "store_name": null}, {"id": 31984, "name": "Бондюэль Красная фасоль в классическом Барбекю ст/б 350 мл", "mech": null, "img_link": "https://media.5ka.ru/media/products/4038159.jpg", "plu": 4038159, "promo": {"id": 1170306661, "date_begin": "2021-04-01", "date_end": "2021-05-05", "type": "", "description": "", "kind": "Z011", "expired_at": 14}, "current_prices": {"price_reg__min": 109.99, "price_promo__min": 79.99}, "store_name": null}, {"id": 28303, "name": "Закусочка венгерская, Дядя Ваня, 460 г", "mech": null, "img_link": "https://media.5ka.ru/media/products/17454.jpg", "plu": 17454, "promo": {"id": 1171092812, "date_begin": "2021-04-08", "date_end": "2021-05-05", "type": "", "description": "", "kind": "Z011", "expired_at": 14}, "current_prices": {"price_reg__min": 119.99, "price_promo__min": 99.99}, "store_name": null}, {"id": 28310, "name": "МОРСКОЙ КОТИК Тунец филе в масле 170г", "mech": null, "img_link": "https://media.5ka.ru/media/products/3373006.jpg", "plu": 3373006, "promo": {"id": 1171092812, "date_begin": "2021-04-08", "date_end": "2021-05-05", "type": "", "description": "", "kind": "Z011", "expired_at": 14}, "current_prices": {"price_reg__min": 110.0, "price_promo__min": 99.99}, "store_name": null}, {"id": 31624, "name": "ВЕРЕС Икра из кабачков ЭКСТРА 505г", "mech": null, "img_link": "https://media.5ka.ru/media/products/51725.jpg", "plu": 51725, "promo": {"id": 1170306661, "date_begin": "2021-04-01", "date_end": "2021-05-05", "type": "", "description": "", "kind": "Z011", "expired_at": 14}, "current_prices": {"price_reg__min": 116.99, "price_promo__min": 99.99}, "store_name": null}, {"id": 31856, "name": "Шпроты из салаки в масле, Знак качества, 240 г", "mech": null, "img_link": "https://media.5ka.ru/media/products/3648434.jpg", "plu": 3648434, "promo": {"id": 1170306661, "date_begin": "2021-04-01", "date_end": "2021-05-05", "type": "", "description": "", "kind": "Z011", "expired_at": 14}, "current_prices": {"price_reg__min": 119.99, "price_promo__min": 109.99}, "store_name": null}, {"id": 31769, "name": "IBERICA Маслины с костью 360г", "mech": null, "img_link": "https://media.5ka.ru/media/products/3466502.jpg", "plu": 3466502, "promo": {"id": 1170306661, "date_begin": "2021-04-01", "date_end": "2021-05-05", "type": "", "description": "", "kind": "Z011", "expired_at": 14}, "current_prices": {"price_reg__min": 125.0, "price_promo__min": 119.99}, "store_name": null}, {"id": 31893, "name": "JANARAT Имам баялды 450г", "mech": null, "img_link": "https://media.5ka.ru/media/products/3692516.jpg", "plu": 3692516, "promo": {"id": 1170306661, "date_begin": "2021-04-01", "date_end": "2021-05-05", "type": "", "description": "", "kind": "Z011", "expired_at": 14}, "current_prices": {"price_reg__min": 129.99, "price_promo__min": 119.99}, "store_name": null}, {"id": 3835, "name": "Свинина Великолукский МК тушеная ГОСТ 325 г", "mech": null, "img_link": "https://media.5ka.ru/media/products/3675349.jpg", "plu": 3675349, "promo": {"id": 1173707621, "date_begin": "2021-04-20", "date_end": "2021-04-26", "type": "", "description": "", "kind": "Z001", "expired_at": 5}, "current_prices": {"price_reg__min": 149.99, "price_promo__min": 139.99}, "store_name": null}, {"id": 3856, "name": "Говядина тушеная высший сорт 325 гр \nВеликолукский Мясокомбинат", "mech": null, "img_link": "https://media.5ka.ru/media/products/3902643.jpg", "plu": 3902643, "promo": {"id": 1173707621, "date_begin": "2021-04-20", "date_end": "2021-04-26", "type": "", "description": "", "kind": "Z001", "expired_at": 5}, "current_prices": {"price_reg__min": 149.99, "price_promo__min": 139.99}, "store_name": null}]}